proxy_fetcher/__init__.py
proxy_fetcher/core.py
proxy_fetcher-0.3.1.dist-info/METADATA
proxy_fetcher-0.3.1.dist-info/WHEEL
proxy_fetcher-0.3.1.dist-info/top_level.txt
proxy_fetcher-0.3.1.dist-info/RECORD
