Metadata-Version: 2.4
Name: proxy_fetcher
Version: 0.3.1
Summary: Package for fetching and validating working HTTP/HTTPS proxies from multiple sources
Home-page: https://github.com/ilmir-muslim/proxy-fetcher
Author: Ilmir Gilmiiarov
Author-email: ilmir_gf@mail.ru
Project-URL: Bug Reports, https://github.com/ilmir-muslim/proxy-fetcher/issues
Project-URL: Source, https://github.com/ilmir-muslim/proxy-fetcher
Keywords: proxy scraper validator fetcher
Classifier: Development Status :: 4 - Beta
Classifier: Intended Audience :: Developers
Classifier: Topic :: Internet :: Proxy Servers
Classifier: Programming Language :: Python :: 3.13
Classifier: License :: OSI Approved :: MIT License
Classifier: Operating System :: OS Independent
Requires-Python: >=3.11
Requires-Dist: requests>=2.25.1
Requires-Dist: tqdm>=4.60.0
Requires-Dist: aiohttp>=3.9.0
Requires-Dist: typing_extensions>=4.0.0
Dynamic: author
Dynamic: author-email
Dynamic: classifier
Dynamic: description
Dynamic: description-content-type
Dynamic: home-page
Dynamic: keywords
Dynamic: project-url
Dynamic: requires-dist
Dynamic: requires-python
Dynamic: summary
